dapla_team_cli/__init__.py
dapla_team_cli/__main__.py
dapla_team_cli/api/__init__.py
dapla_team_cli/api/api_request.py
dapla_team_cli/api/models/__init__.py
dapla_team_cli/api/models/group.py
dapla_team_cli/api/models/link.py
dapla_team_cli/api/models/team.py
dapla_team_cli/api/models/user.py
dapla_team_cli/api/utils.py
dapla_team_cli/auth/__init__.py
dapla_team_cli/auth/cmd.py
dapla_team_cli/auth/services/__init__.py
dapla_team_cli/auth/services/expiry.py
dapla_team_cli/auth/services/get_token.py
dapla_team_cli/auth/services/set_token.py
dapla_team_cli/changelogs/__init__.py
dapla_team_cli/changelogs/cmd.py
dapla_team_cli/changelogs/release_logs.py
dapla_team_cli/config.py
dapla_team_cli/doctor/__init__.py
dapla_team_cli/doctor/check.py
dapla_team_cli/doctor/cmd.py
dapla_team_cli/doctor/gcloud.py
dapla_team_cli/doctor/keycloak.py
dapla_team_cli/gcp/__init__.py
dapla_team_cli/gcp/project_roles.json
dapla_team_cli/github.py
dapla_team_cli/groups/__init__.py
dapla_team_cli/groups/cmd.py
dapla_team_cli/groups/groups.py
dapla_team_cli/groups/members/__init__.py
dapla_team_cli/groups/members/cmd.py
dapla_team_cli/groups/members/members.py
dapla_team_cli/groups/services/__init__.py
dapla_team_cli/pr/__init__.py
dapla_team_cli/pr/add/__init__.py
dapla_team_cli/pr/add/cmd.py
dapla_team_cli/pr/approve/__init__.py
dapla_team_cli/pr/approve/approve.py
dapla_team_cli/pr/approve/cmd.py
dapla_team_cli/pr/atlantis_apply/__init__.py
dapla_team_cli/pr/atlantis_apply/atlantis_apply_all.py
dapla_team_cli/pr/atlantis_apply/cmd.py
dapla_team_cli/pr/atlantis_plan/__init__.py
dapla_team_cli/pr/atlantis_plan/atlantis_plan_all.py
dapla_team_cli/pr/atlantis_plan/cmd.py
dapla_team_cli/pr/batch_handler.py
dapla_team_cli/pr/cmd.py
dapla_team_cli/pr/const.py
dapla_team_cli/pr/janitor/__init__.py
dapla_team_cli/pr/janitor/close_all.py
dapla_team_cli/pr/janitor/cmd.py
dapla_team_cli/pr/merge/__init__.py
dapla_team_cli/pr/merge/cmd.py
dapla_team_cli/pr/merge/merge_all.py
dapla_team_cli-0.3.7.dist-info/LICENSE
dapla_team_cli-0.3.7.dist-info/METADATA
dapla_team_cli-0.3.7.dist-info/WHEEL
dapla_team_cli-0.3.7.dist-info/entry_points.txt
dapla_team_cli-0.3.7.dist-info/RECORD
