Metadata-Version: 2.1
Name: dapla-team-cli
Version: 0.3.7
Summary: CLI for working with Dapla Teams
Home-page: https://github.com/statisticsnorway/dapla-team-cli
License: MIT
Author: Kenneth Leine Schulstad
Author-email: kls@rdck.no
Requires-Python: >=3.10.0,<3.12
Classifier: Development Status :: 2 - Pre-Alpha
Classifier: Environment :: Console
Classifier: License :: OSI Approved :: MIT License
Classifier: Programming Language :: Python :: 3
Classifier: Programming Language :: Python :: 3.10
Classifier: Programming Language :: Python :: 3.11
Classifier: Typing :: Typed
Requires-Dist: azure-cli (>=2.48.1)
Requires-Dist: click (>=8.1.3)
Requires-Dist: click-config-file (>=0.6.0)
Requires-Dist: click-configfile (>=0.2.3)
Requires-Dist: devtools (>=0.11.0)
Requires-Dist: gitpython (>=3.1.31)
Requires-Dist: google-cloud-secret-manager (>=2.16.1)
Requires-Dist: google-cloud-storage (>=2.9.0)
Requires-Dist: jinja2 (>=3.1.2)
Requires-Dist: jupyterhub (>=4.0.0)
Requires-Dist: pendulum (>=2.1,<3.0)
Requires-Dist: pydantic (>=2.5,<3.0)
Requires-Dist: python-hcl2 (>=4.3.1)
Requires-Dist: python-tfvars (>=0.1.0)
Requires-Dist: questionary (>=1.10.0)
Requires-Dist: requests (>=2.30.0)
Requires-Dist: returns (>=0.20.0)
Requires-Dist: rich (>=13.3.5)
Requires-Dist: sqlalchemy (>=2.0.13)
Requires-Dist: twine (>=4.0.2)
Requires-Dist: typeguard (>=3.0.2)
Requires-Dist: typer (>=0.9.0)
Requires-Dist: types-google-cloud-ndb (>=2.1.0.7)
Project-URL: Changelog, https://github.com/statisticsnorway/dapla-team-cli/releases
Project-URL: Documentation, https://statisticsnorway.github.io/dapla-team-cli
Project-URL: Repository, https://github.com/statisticsnorway/dapla-team-cli
